smartchunkllm/__init__.py
smartchunkllm/cli.py
smartchunkllm/processor.py
smartchunkllm/ai/__init__.py
smartchunkllm/ai/classification.py
smartchunkllm/ai/clustering.py
smartchunkllm/ai/embeddings.py
smartchunkllm/ai/quality.py
smartchunkllm/ai/transformers.py
smartchunkllm/core/__init__.py
smartchunkllm/core/chunk.py
smartchunkllm/core/config.py
smartchunkllm/core/exceptions.py
smartchunkllm/core/processor.py
smartchunkllm/core/types.py
smartchunkllm/legal/__init__.py
smartchunkllm/legal/analyzer.py
smartchunkllm/legal/processor.py
smartchunkllm/legal/validator.py
smartchunkllm/llm/__init__.py
smartchunkllm/llm/processors.py
smartchunkllm/llm/prompts.py
smartchunkllm/llm/providers.py
smartchunkllm/pdf/__init__.py
smartchunkllm/pdf/extractor.py
smartchunkllm/pdf/font.py
smartchunkllm/pdf/layout.py
smartchunkllm/pdf/ocr.py
smartchunkllm/pdf/structure.py
smartchunkllm/utils/__init__.py
smartchunkllm/utils/file.py
smartchunkllm/utils/logging.py
smartchunkllm/utils/memory.py
smartchunkllm/utils/performance.py
smartchunkllm/utils/system.py
smartchunkllm/utils/text.py
smartchunkllm/utils/validation.py
smartchunkllm-0.1.7.dist-info/licenses/LICENSE
smartchunkllm-0.1.7.dist-info/METADATA
smartchunkllm-0.1.7.dist-info/WHEEL
smartchunkllm-0.1.7.dist-info/entry_points.txt
smartchunkllm-0.1.7.dist-info/top_level.txt
smartchunkllm-0.1.7.dist-info/RECORD
