Metadata-Version: 2.4
Name: smartchunkllm
Version: 0.1.7
Summary: Advanced Legal Document Semantic Chunking System
Home-page: https://github.com/smartchunkllm/smartchunkllm
Download-URL: https://github.com/smartchunkllm/smartchunkllm/archive/v1.0.0.tar.gz
Author: SmartChunkLLM Team
Author-email: SmartChunkLLM Team <info@smartchunkllm.com>
Maintainer: SmartChunkLLM Team
Maintainer-email: SmartChunkLLM Team <info@smartchunkllm.com>
License: MIT
Project-URL: Homepage, https://github.com/smartchunkllm/smartchunkllm
Project-URL: Repository, https://github.com/smartchunkllm/smartchunkllm
Project-URL: Documentation, https://smartchunkllm.readthedocs.io/
Project-URL: Bug Reports, https://github.com/smartchunkllm/smartchunkllm/issues
Project-URL: Changelog, https://github.com/smartchunkllm/smartchunkllm/blob/main/CHANGELOG.md
Keywords: legal,documents,semantic,chunking,nlp,ai,llm,pdf,turkish,law,embedding,clustering,transformers,ollama,openai,anthropic
Platform: any
Classifier: Development Status :: 4 - Beta
Classifier: Intended Audience :: Legal Industry
Classifier: Intended Audience :: Developers
Classifier: Intended Audience :: Science/Research
Classifier: License :: OSI Approved :: MIT License
Classifier: Operating System :: OS Independent
Classifier: Programming Language :: Python :: 3
Classifier: Programming Language :: Python :: 3.8
Classifier: Programming Language :: Python :: 3.9
Classifier: Programming Language :: Python :: 3.10
Classifier: Programming Language :: Python :: 3.11
Classifier: Programming Language :: Python :: 3.12
Classifier: Topic :: Text Processing :: Linguistic
Classifier: Topic :: Scientific/Engineering :: Artificial Intelligence
Classifier: Topic :: Office/Business
Classifier: Topic :: Software Development :: Libraries :: Python Modules
Requires-Python: >=3.8
License-File: LICENSE
Requires-Dist: numpy>=1.26.0
Requires-Dist: scipy>=1.11.0
Requires-Dist: pandas>=2.1.0
Requires-Dist: PyPDF2>=3.0.1
Requires-Dist: pdfplumber>=0.10.0
Requires-Dist: pymupdf>=1.23.26
Requires-Dist: pdfminer.six>=20231228
Requires-Dist: pytesseract>=0.3.10
Requires-Dist: Pillow>=10.0.0
Requires-Dist: opencv-python>=4.8.0
Requires-Dist: transformers>=4.36.0
Requires-Dist: sentence-transformers>=2.2.2
Requires-Dist: scikit-learn>=1.3.0
Requires-Dist: hdbscan>=0.8.33
Requires-Dist: umap-learn>=0.5.9
Requires-Dist: openai>=1.6.0
Requires-Dist: anthropic>=0.8.0
Requires-Dist: ollama>=0.1.7
Requires-Dist: pydantic>=2.5.0
Requires-Dist: tqdm>=4.66.0
Requires-Dist: click>=8.1.0
Requires-Dist: rich>=13.7.0
Requires-Dist: loguru>=0.7.0
Requires-Dist: pyyaml>=6.0.1
Requires-Dist: joblib>=1.3.0
Requires-Dist: requests>=2.31.0
Requires-Dist: httpx>=0.25.0
Requires-Dist: typing-extensions>=4.8.0
Provides-Extra: turkish
Requires-Dist: zeyrek>=0.1.2; extra == "turkish"
Requires-Dist: turkish-stemmer>=1.0.0; extra == "turkish"
Provides-Extra: layout
Requires-Dist: layoutparser>=0.3.4; extra == "layout"
Requires-Dist: detectron2>=0.6; python_version < "3.11" and extra == "layout"
Requires-Dist: torch>=2.1.0; extra == "layout"
Requires-Dist: torchvision>=0.16.0; extra == "layout"
Provides-Extra: performance
Requires-Dist: numba>=0.60.0; extra == "performance"
Requires-Dist: llvmlite>=0.43.0; extra == "performance"
Requires-Dist: faiss-cpu>=1.7.4; extra == "performance"
Provides-Extra: visualization
Requires-Dist: matplotlib>=3.8.0; extra == "visualization"
Requires-Dist: seaborn>=0.13.0; extra == "visualization"
Requires-Dist: plotly>=5.17.0; extra == "visualization"
Provides-Extra: web
Requires-Dist: streamlit>=1.29.0; extra == "web"
Requires-Dist: fastapi>=0.104.0; extra == "web"
Requires-Dist: uvicorn>=0.24.0; extra == "web"
Provides-Extra: database
Requires-Dist: sqlalchemy>=2.0.0; extra == "database"
Requires-Dist: psycopg2-binary>=2.9.9; extra == "database"
Provides-Extra: cloud
Requires-Dist: boto3>=1.34.0; extra == "cloud"
Requires-Dist: azure-storage-blob>=12.19.0; extra == "cloud"
Requires-Dist: google-cloud-storage>=2.10.0; extra == "cloud"
Provides-Extra: dev
Requires-Dist: pytest>=7.4.0; extra == "dev"
Requires-Dist: pytest-cov>=4.1.0; extra == "dev"
Requires-Dist: pytest-asyncio>=0.21.0; extra == "dev"
Requires-Dist: black>=23.11.0; extra == "dev"
Requires-Dist: flake8>=6.1.0; extra == "dev"
Requires-Dist: mypy>=1.7.0; extra == "dev"
Requires-Dist: isort>=5.12.0; extra == "dev"
Provides-Extra: docs
Requires-Dist: sphinx>=7.2.0; extra == "docs"
Requires-Dist: sphinx-rtd-theme>=1.3.0; extra == "docs"
Provides-Extra: all
Requires-Dist: zeyrek>=0.1.2; extra == "all"
Requires-Dist: turkish-stemmer>=1.0.0; extra == "all"
Requires-Dist: layoutparser>=0.3.4; extra == "all"
Requires-Dist: detectron2>=0.6; python_version < "3.11" and extra == "all"
Requires-Dist: torch>=2.1.0; extra == "all"
Requires-Dist: torchvision>=0.16.0; extra == "all"
Requires-Dist: numba>=0.60.0; extra == "all"
Requires-Dist: llvmlite>=0.43.0; extra == "all"
Requires-Dist: faiss-cpu>=1.7.4; extra == "all"
Requires-Dist: matplotlib>=3.8.0; extra == "all"
Requires-Dist: seaborn>=0.13.0; extra == "all"
Requires-Dist: plotly>=5.17.0; extra == "all"
Requires-Dist: streamlit>=1.29.0; extra == "all"
Requires-Dist: fastapi>=0.104.0; extra == "all"
Requires-Dist: uvicorn>=0.24.0; extra == "all"
Requires-Dist: sqlalchemy>=2.0.0; extra == "all"
Requires-Dist: psycopg2-binary>=2.9.9; extra == "all"
Requires-Dist: boto3>=1.34.0; extra == "all"
Requires-Dist: azure-storage-blob>=12.19.0; extra == "all"
Requires-Dist: google-cloud-storage>=2.10.0; extra == "all"
Requires-Dist: pytest>=7.4.0; extra == "all"
Requires-Dist: pytest-cov>=4.1.0; extra == "all"
Requires-Dist: pytest-asyncio>=0.21.0; extra == "all"
Requires-Dist: black>=23.11.0; extra == "all"
Requires-Dist: flake8>=6.1.0; extra == "all"
Requires-Dist: mypy>=1.7.0; extra == "all"
Requires-Dist: isort>=5.12.0; extra == "all"
Requires-Dist: sphinx>=7.2.0; extra == "all"
Requires-Dist: sphinx-rtd-theme>=1.3.0; extra == "all"
Dynamic: author
Dynamic: download-url
Dynamic: home-page
Dynamic: license-file
Dynamic: maintainer
Dynamic: platform
Dynamic: requires-python
